feectools/__init__.py
feectools/version.py
feectools/accelerate/__init__.py
feectools/accelerate/accelerate.py
feectools/accelerate/compile_psydac.mk
feectools/api/__init__.py
feectools/api/essential_bc.py
feectools/api/fem_bilinear_form.py
feectools/api/fem_common.py
feectools/api/fem_sum_form.py
feectools/api/settings.py
feectools/core/__init__.py
feectools/core/bsplines.py
feectools/core/bsplines_kernels.py
feectools/core/field_evaluation_kernels.py
feectools/core/tests/__init__.py
feectools/core/tests/test_bsplines.py
feectools/core/tests/test_bsplines_kernel.py
feectools/core/tests/test_bsplines_pyccel.py
feectools/ddm/__init__.py
feectools/ddm/basic.py
feectools/ddm/blocking_data_exchanger.py
feectools/ddm/cart.py
feectools/ddm/interface_data_exchanger.py
feectools/ddm/mpi.py
feectools/ddm/nonblocking_data_exchanger.py
feectools/ddm/partition.py
feectools/ddm/petsc.py
feectools/ddm/utilities.py
feectools/ddm/tests/__init__.py
feectools/ddm/tests/test_cart_1d.py
feectools/ddm/tests/test_cart_2d.py
feectools/ddm/tests/test_cart_3d.py
feectools/ddm/tests/test_multicart_2d.py
feectools/ddm/tests/test_partition.py
feectools/feec/__init__.py
feectools/feec/derivatives.py
feectools/feec/dof_kernels.py
feectools/feec/global_geometric_projectors.py
feectools/feec/hodge.py
feectools/fem/__init__.py
feectools/fem/basic.py
feectools/fem/grid.py
feectools/fem/partitioning.py
feectools/fem/projectors.py
feectools/fem/splines.py
feectools/fem/tensor.py
feectools/fem/vector.py
feectools/fem/tests/__init__.py
feectools/fem/tests/analytical_profiles_1d.py
feectools/fem/tests/analytical_profiles_base.py
feectools/fem/tests/splines_error_bounds.py
feectools/fem/tests/test_spline_histopolation.py
feectools/fem/tests/test_spline_interpolation.py
feectools/fem/tests/test_splines.py
feectools/fem/tests/test_splines_par.py
feectools/fem/tests/test_vector_spaces.py
feectools/fem/tests/utilities.py
feectools/linalg/__init__.py
feectools/linalg/basic.py
feectools/linalg/block.py
feectools-0.1.3.dist-info/licenses/AUTHORS
feectools-0.1.3.dist-info/licenses/LICENSE
feectools-0.1.3.dist-info/METADATA
feectools-0.1.3.dist-info/WHEEL
feectools-0.1.3.dist-info/entry_points.txt
feectools-0.1.3.dist-info/top_level.txt
feectools-0.1.3.dist-info/RECORD
