Metadata-Version: 2.4
Name: feectools
Version: 0.1.3
Summary: Slimmed-down fork of Psydac (https://github.com/pyccel/psydac) with less functionality and fewer dependencies.
Author-email: Psydac development team <psydac@googlegroups.com>
Maintainer-email: Stefan Possanner <stefan.possanner@ipp.mpg.de>, Max Lindqvist <max.lindqvist@ipp.mpg.de>, Yaman Güçlü <yaman.guclu@gmail.com>, Martin Campos Pinto <martin.campos-pinto@ipp.mpg.de>, Ahmed Ratnani <ratnaniahmed@gmail.com>
License: MIT License
Project-URL: Homepage, https://github.com/struphy-hub/feectools
Project-URL: Documentation, https://github.com/struphy-hub/feectools
Project-URL: Repository, https://github.com/struphy-hub/feectools
Keywords: FEM,IGA,B-spline,NURBS
Classifier: Programming Language :: Python :: 3
Requires-Python: >=3.10
License-File: LICENSE
License-File: AUTHORS
Requires-Dist: numpy>=1.16
Requires-Dist: scipy>=1.12
Requires-Dist: sympy>=1.5
Requires-Dist: matplotlib
Requires-Dist: pyyaml>=5.1
Requires-Dist: packaging
Requires-Dist: pyevtk
Requires-Dist: pyccel>=2.1.0
Requires-Dist: h5py
Requires-Dist: tblib
Provides-Extra: test
Requires-Dist: pytest-cov>=5.0.0; extra == "test"
Requires-Dist: pytest>=4.5; extra == "test"
Requires-Dist: pytest-xdist>=1.16; extra == "test"
Requires-Dist: pytest-testmon; extra == "test"
Requires-Dist: Pillow; extra == "test"
Provides-Extra: mpi
Requires-Dist: mpi4py>=4; extra == "mpi"
Dynamic: license-file
